{
  "count": 20,
  "start": 0,
  "total": 79,
  "subjects": [
    {
      "rating": {
        "max": 10,
        "average": 7,
        "stars": "35",
        "min": 0
      },
      "genres": [
        "剧情",
        "动作",
        "爱情"
      ],
      "title": "间谍同盟",
      "casts": [
        {
          "alt": "https://movie.douban.com/celebrity/1054452/",
          "avatars": {
            "small": "http://img7.doubanio.com/img/celebrity/small/1604.jpg",
            "large": "http://img7.doubanio.com/img/celebrity/large/1604.jpg",
            "medium": "http://img7.doubanio.com/img/celebrity/medium/1604.jpg"
          },
          "name": "布拉德·皮特",
          "id": "1054452"
        },
        {
          "alt": "https://movie.douban.com/celebrity/1006955/",
          "avatars": {
            "small": "http://img3.doubanio.com/img/celebrity/small/36117.jpg",
            "large": "http://img3.doubanio.com/img/celebrity/large/36117.jpg",
            "medium": "http://img3.doubanio.com/img/celebrity/medium/36117.jpg"
          },
          "name": "玛丽昂·歌迪亚",
          "id": "1006955"
        },
        {
          "alt": "https://movie.douban.com/celebrity/1000008/",
          "avatars": {
            "small": "http://img3.doubanio.com/img/celebrity/small/2817.jpg",
            "large": "http://img3.doubanio.com/img/celebrity/large/2817.jpg",
            "medium": "http://img3.doubanio.com/img/celebrity/medium/2817.jpg"
          },
          "name": "马修·古迪",
          "id": "1000008"
        }
      ],
      "collect_count": 692,
      "original_title": "Allied",
      "subtype": "movie",
      "directors": [
        {
          "alt": "https://movie.douban.com/celebrity/1053564/",
          "avatars": {
            "small": "http://img7.doubanio.com/img/celebrity/small/505.jpg",
            "large": "http://img7.doubanio.com/img/celebrity/large/505.jpg",
            "medium": "http://img7.doubanio.com/img/celebrity/medium/505.jpg"
          },
          "name": "罗伯特·泽米吉斯",
          "id": "1053564"
        }
      ],
      "year": "2016",
      "images": {
        "small": "http://img3.doubanio.com/view/movie_poster_cover/ipst/public/p2399977609.jpg",
        "large": "http://img3.doubanio.com/view/movie_poster_cover/lpst/public/p2399977609.jpg",
        "medium": "http://img3.doubanio.com/view/movie_poster_cover/spst/public/p2399977609.jpg"
      },
      "alt": "https://movie.douban.com/subject/25978126/",
      "id": "25978126"
    },
    {
      "rating": {
        "max": 10,
        "average": 0,
        "stars": "00",
        "min": 0
      },
      "genres": [
        "剧情",
        "爱情",
        "悬疑"
      ],
      "title": "爱你的人",
      "casts": [
        {
          "alt": "https://movie.douban.com/celebrity/1317855/",
          "avatars": {
            "small": "http://img3.doubanio.com/img/celebrity/small/41469.jpg",
            "large": "http://img3.doubanio.com/img/celebrity/large/41469.jpg",
            "medium": "http://img3.doubanio.com/img/celebrity/medium/41469.jpg"
          },
          "name": "郑昊",
          "id": "1317855"
        },
        {
          "alt": "https://movie.douban.com/celebrity/1353627/",
          "avatars": {
            "small": "http://img3.doubanio.com/img/celebrity/small/1458219561.78.jpg",
            "large": "http://img3.doubanio.com/img/celebrity/large/1458219561.78.jpg",
            "medium": "http://img3.doubanio.com/img/celebrity/medium/1458219561.78.jpg"
          },
          "name": "张墨锡",
          "id": "1353627"
        },
        {
          "alt": "https://movie.douban.com/celebrity/1352325/",
          "avatars": {
            "small": "http://img7.doubanio.com/img/celebrity/small/2g4J5GjYmUwcel_avatar_uploaded1444705377.93.jpg",
            "large": "http://img7.doubanio.com/img/celebrity/large/2g4J5GjYmUwcel_avatar_uploaded1444705377.93.jpg",
            "medium": "http://img7.doubanio.com/img/celebrity/medium/2g4J5GjYmUwcel_avatar_uploaded1444705377.93.jpg"
          },
          "name": "柯伊玟",
          "id": "1352325"
        }
      ],
      "collect_count": 19,
      "original_title": "爱你的人",
      "subtype": "movie",
      "directors": [
        {
          "alt": "https://movie.douban.com/celebrity/1360162/",
          "avatars": {
            "small": "http://img3.doubanio.com/f/movie/ca527386eb8c4e325611e22dfcb04cc116d6b423/pics/movie/celebrity-default-small.png",
            "large": "http://img7.doubanio.com/f/movie/63acc16ca6309ef191f0378faf793d1096a3e606/pics/movie/celebrity-default-large.png",
            "medium": "http://img3.doubanio.com/f/movie/8dd0c794499fe925ae2ae89ee30cd225750457b4/pics/movie/celebrity-default-medium.png"
          },
          "name": "谢云鹏",
          "id": "1360162"
        },
        {
          "alt": "https://movie.douban.com/celebrity/1360163/",
          "avatars": {
            "small": "http://img7.doubanio.com/img/celebrity/small/1479700954.85.jpg",
            "large": "http://img7.doubanio.com/img/celebrity/large/1479700954.85.jpg",
            "medium": "http://img7.doubanio.com/img/celebrity/medium/1479700954.85.jpg"
          },
          "name": "杜昌博",
          "id": "1360163"
        }
      ],
      "year": "2016",
      "images": {
        "small": "http://img3.doubanio.com/view/movie_poster_cover/ipst/public/p2395560907.jpg",
        "large": "http://img3.doubanio.com/view/movie_poster_cover/lpst/public/p2395560907.jpg",
        "medium": "http://img3.doubanio.com/view/movie_poster_cover/spst/public/p2395560907.jpg"
      },
      "alt": "https://movie.douban.com/subject/25899612/",
      "id": "25899612"
    },
    {
      "rating": {
        "max": 10,
        "average": 8.9,
        "stars": "45",
        "min": 0
      },
      "genres": [
        "剧情",
        "爱情",
        "动画"
      ],
      "title": "你的名字。",
      "casts": [
        {
          "alt": "https://movie.douban.com/celebrity/1185637/",
          "avatars": {
            "small": "http://img3.doubanio.com/img/celebrity/small/13768.jpg",
            "large": "http://img3.doubanio.com/img/celebrity/large/13768.jpg",
            "medium": "http://img3.doubanio.com/img/celebrity/medium/13768.jpg"
          },
          "name": "神木隆之介",
          "id": "1185637"
        },
        {
          "alt": "https://movie.douban.com/celebrity/1316660/",
          "avatars": {
            "small": "http://img3.doubanio.com/img/celebrity/small/1445093052.07.jpg",
            "large": "http://img3.doubanio.com/img/celebrity/large/1445093052.07.jpg",
            "medium": "http://img3.doubanio.com/img/celebrity/medium/1445093052.07.jpg"
          },
          "name": "上白石萌音",
          "id": "1316660"
        },
        {
          "alt": "https://movie.douban.com/celebrity/1018667/",
          "avatars": {
            "small": "http://img7.doubanio.com/img/celebrity/small/36735.jpg",
            "large": "http://img7.doubanio.com/img/celebrity/large/36735.jpg",
            "medium": "http://img7.doubanio.com/img/celebrity/medium/36735.jpg"
          },
          "name": "长泽雅美",
          "id": "1018667"
        }
      ],
      "collect_count": 81757,
      "original_title": "君の名は。",
      "subtype": "movie",
      "directors": [
        {
          "alt": "https://movie.douban.com/celebrity/1005177/",
          "avatars": {
            "small": "http://img3.doubanio.com/img/celebrity/small/1118.jpg",
            "large": "http://img3.doubanio.com/img/celebrity/large/1118.jpg",
            "medium": "http://img3.doubanio.com/img/celebrity/medium/1118.jpg"
          },
          "name": "新海诚",
          "id": "1005177"
        }
      ],
      "year": "2016",
      "images": {
        "small": "http://img3.doubanio.com/view/movie_poster_cover/ipst/public/p2395733377.jpg",
        "large": "http://img3.doubanio.com/view/movie_poster_cover/lpst/public/p2395733377.jpg",
        "medium": "http://img3.doubanio.com/view/movie_poster_cover/spst/public/p2395733377.jpg"
      },
      "alt": "https://movie.douban.com/subject/26683290/",
      "id": "26683290"
    },
    {
      "rating": {
        "max": 10,
        "average": 7.2,
        "stars": "40",
        "min": 0
      },
      "genres": [
        "剧情",
        "奇幻",
        "冒险"
      ],
      "title": "佩小姐的奇幻城堡",
      "casts": [
        {
          "alt": "https://movie.douban.com/celebrity/1000220/",
          "avatars": {
            "small": "http://img3.doubanio.com/img/celebrity/small/44226.jpg",
            "large": "http://img3.doubanio.com/img/celebrity/large/44226.jpg",
            "medium": "http://img3.doubanio.com/img/celebrity/medium/44226.jpg"
          },
          "name": "阿萨·巴特菲尔德",
          "id": "1000220"
        },
        {
          "alt": "https://movie.douban.com/celebrity/1025155/",
          "avatars": {
            "small": "http://img7.doubanio.com/img/celebrity/small/25343.jpg",
            "large": "http://img7.doubanio.com/img/celebrity/large/25343.jpg",
            "medium": "http://img7.doubanio.com/img/celebrity/medium/25343.jpg"
          },
          "name": "伊娃·格林",
          "id": "1025155"
        },
        {
          "alt": "https://movie.douban.com/celebrity/1054408/",
          "avatars": {
            "small": "http://img7.doubanio.com/img/celebrity/small/31870.jpg",
            "large": "http://img7.doubanio.com/img/celebrity/large/31870.jpg",
            "medium": "http://img7.doubanio.com/img/celebrity/medium/31870.jpg"
          },
          "name": "塞缪尔·杰克逊",
          "id": "1054408"
        }
      ],
      "collect_count": 8092,
      "original_title": "Miss Peregrine's Home for Peculiar Children",
      "subtype": "movie",
      "directors": [
        {
          "alt": "https://movie.douban.com/celebrity/1019002/",
          "avatars": {
            "small": "http://img7.doubanio.com/img/celebrity/small/215.jpg",
            "large": "http://img7.doubanio.com/img/celebrity/large/215.jpg",
            "medium": "http://img7.doubanio.com/img/celebrity/medium/215.jpg"
          },
          "name": "蒂姆·波顿",
          "id": "1019002"
        }
      ],
      "year": "2016",
      "images": {
        "small": "http://img7.doubanio.com/view/movie_poster_cover/ipst/public/p2391127930.jpg",
        "large": "http://img7.doubanio.com/view/movie_poster_cover/lpst/public/p2391127930.jpg",
        "medium": "http://img7.doubanio.com/view/movie_poster_cover/spst/public/p2391127930.jpg"
      },
      "alt": "https://movie.douban.com/subject/7051830/",
      "id": "7051830"
    },
    {
      "rating": {
        "max": 10,
        "average": 0,
        "stars": "00",
        "min": 0
      },
      "genres": [
        "喜剧",
        "爱情",
        "奇幻"
      ],
      "title": "28岁未成年",
      "casts": [
        {
          "alt": "https://movie.douban.com/celebrity/1315861/",
          "avatars": {
            "small": "http://img3.doubanio.com/img/celebrity/small/57286.jpg",
            "large": "http://img3.doubanio.com/img/celebrity/large/57286.jpg",
            "medium": "http://img3.doubanio.com/img/celebrity/medium/57286.jpg"
          },
          "name": "倪妮",
          "id": "1315861"
        },
        {
          "alt": "https://movie.douban.com/celebrity/1015713/",
          "avatars": {
            "small": "http://img3.doubanio.com/img/celebrity/small/1414655610.66.jpg",
            "large": "http://img3.doubanio.com/img/celebrity/large/1414655610.66.jpg",
            "medium": "http://img3.doubanio.com/img/celebrity/medium/1414655610.66.jpg"
          },
          "name": "霍建华",
          "id": "1015713"
        },
        {
          "alt": "https://movie.douban.com/celebrity/1275459/",
          "avatars": {
            "small": "http://img7.doubanio.com/img/celebrity/small/1376103579.93.jpg",
            "large": "http://img7.doubanio.com/img/celebrity/large/1376103579.93.jpg",
            "medium": "http://img7.doubanio.com/img/celebrity/medium/1376103579.93.jpg"
          },
          "name": "马苏",
          "id": "1275459"
        }
      ],
      "collect_count": 443,
      "original_title": "28岁未成年",
      "subtype": "movie",
      "directors": [
        {
          "alt": "https://movie.douban.com/celebrity/1329527/",
          "avatars": {
            "small": "http://img7.doubanio.com/img/celebrity/small/1369799083.4.jpg",
            "large": "http://img7.doubanio.com/img/celebrity/large/1369799083.4.jpg",
            "medium": "http://img7.doubanio.com/img/celebrity/medium/1369799083.4.jpg"
          },
          "name": "张末",
          "id": "1329527"
        }
      ],
      "year": "2016",
      "images": {
        "small": "http://img3.doubanio.com/view/movie_poster_cover/ipst/public/p2398175718.jpg",
        "large": "http://img3.doubanio.com/view/movie_poster_cover/lpst/public/p2398175718.jpg",
        "medium": "http://img3.doubanio.com/view/movie_poster_cover/spst/public/p2398175718.jpg"
      },
      "alt": "https://movie.douban.com/subject/26658568/",
      "id": "26658568"
    },
    {
      "rating": {
        "max": 10,
        "average": 0,
        "stars": "00",
        "min": 0
      },
      "genres": [
        "剧情",
        "动作",
        "武侠"
      ],
      "title": "三少爷的剑",
      "casts": [
        {
          "alt": "https://movie.douban.com/celebrity/1314535/",
          "avatars": {
            "small": "http://img3.doubanio.com/img/celebrity/small/1398676888.79.jpg",
            "large": "http://img3.doubanio.com/img/celebrity/large/1398676888.79.jpg",
            "medium": "http://img3.doubanio.com/img/celebrity/medium/1398676888.79.jpg"
          },
          "name": "林更新",
          "id": "1314535"
        },
        {
          "alt": "https://movie.douban.com/celebrity/1050590/",
          "avatars": {
            "small": "http://img7.doubanio.com/img/celebrity/small/3030.jpg",
            "large": "http://img7.doubanio.com/img/celebrity/large/3030.jpg",
            "medium": "http://img7.doubanio.com/img/celebrity/medium/3030.jpg"
          },
          "name": "何润东",
          "id": "1050590"
        },
        {
          "alt": "https://movie.douban.com/celebrity/1274286/",
          "avatars": {
            "small": "http://img7.doubanio.com/img/celebrity/small/823.jpg",
            "large": "http://img7.doubanio.com/img/celebrity/large/823.jpg",
            "medium": "http://img7.doubanio.com/img/celebrity/medium/823.jpg"
          },
          "name": "江一燕",
          "id": "1274286"
        }
      ],
      "collect_count": 394,
      "original_title": "三少爷的剑",
      "subtype": "movie",
      "directors": [
        {
          "alt": "https://movie.douban.com/celebrity/1274289/",
          "avatars": {
            "small": "http://img3.doubanio.com/img/celebrity/small/1927.jpg",
            "large": "http://img3.doubanio.com/img/celebrity/large/1927.jpg",
            "medium": "http://img3.doubanio.com/img/celebrity/medium/1927.jpg"
          },
          "name": "尔冬升",
          "id": "1274289"
        }
      ],
      "year": "2016",
      "images": {
        "small": "http://img3.doubanio.com/view/movie_poster_cover/ipst/public/p2399366116.jpg",
        "large": "http://img3.doubanio.com/view/movie_poster_cover/lpst/public/p2399366116.jpg",
        "medium": "http://img3.doubanio.com/view/movie_poster_cover/spst/public/p2399366116.jpg"
      },
      "alt": "https://movie.douban.com/subject/21350556/",
      "id": "21350556"
    },
    {
      "rating": {
        "max": 10,
        "average": 0,
        "stars": "00",
        "min": 0
      },
      "genres": [
        "动作",
        "惊悚"
      ],
      "title": "极速之巅",
      "casts": [
        {
          "alt": "https://movie.douban.com/celebrity/1036341/",
          "avatars": {
            "small": "http://img3.doubanio.com/img/celebrity/small/4078.jpg",
            "large": "http://img3.doubanio.com/img/celebrity/large/4078.jpg",
            "medium": "http://img3.doubanio.com/img/celebrity/medium/4078.jpg"
          },
          "name": "尼古拉斯·霍尔特",
          "id": "1036341"
        },
        {
          "alt": "https://movie.douban.com/celebrity/1013981/",
          "avatars": {
            "small": "http://img7.doubanio.com/img/celebrity/small/42373.jpg",
            "large": "http://img7.doubanio.com/img/celebrity/large/42373.jpg",
            "medium": "http://img7.doubanio.com/img/celebrity/medium/42373.jpg"
          },
          "name": "菲丽希缇·琼斯",
          "id": "1013981"
        },
        {
          "alt": "https://movie.douban.com/celebrity/1054393/",
          "avatars": {
            "small": "http://img3.doubanio.com/img/celebrity/small/1374649659.58.jpg",
            "large": "http://img3.doubanio.com/img/celebrity/large/1374649659.58.jpg",
            "medium": "http://img3.doubanio.com/img/celebrity/medium/1374649659.58.jpg"
          },
          "name": "本·金斯利",
          "id": "1054393"
        }
      ],
      "collect_count": 36,
      "original_title": "Autobahn",
      "subtype": "movie",
      "directors": [
        {
          "alt": "https://movie.douban.com/celebrity/1310081/",
          "avatars": {
            "small": "http://img7.doubanio.com/img/celebrity/small/1440861261.62.jpg",
            "large": "http://img7.doubanio.com/img/celebrity/large/1440861261.62.jpg",
            "medium": "http://img7.doubanio.com/img/celebrity/medium/1440861261.62.jpg"
          },
          "name": "伊兰·克里维",
          "id": "1310081"
        }
      ],
      "year": "2016",
      "images": {
        "small": "http://img3.doubanio.com/view/movie_poster_cover/ipst/public/p2400068929.jpg",
        "large": "http://img3.doubanio.com/view/movie_poster_cover/lpst/public/p2400068929.jpg",
        "medium": "http://img3.doubanio.com/view/movie_poster_cover/spst/public/p2400068929.jpg"
      },
      "alt": "https://movie.douban.com/subject/25708452/",
      "id": "25708452"
    },
    {
      "rating": {
        "max": 10,
        "average": 0,
        "stars": "00",
        "min": 0
      },
      "genres": [
        "喜剧",
        "动作"
      ],
      "title": "超级快递",
      "casts": [
        {
          "alt": "https://movie.douban.com/celebrity/1313841/",
          "avatars": {
            "small": "http://img3.doubanio.com/img/celebrity/small/1420296836.46.jpg",
            "large": "http://img3.doubanio.com/img/celebrity/large/1420296836.46.jpg",
            "medium": "http://img3.doubanio.com/img/celebrity/medium/1420296836.46.jpg"
          },
          "name": "陈赫",
          "id": "1313841"
        },
        {
          "alt": "https://movie.douban.com/celebrity/1023418/",
          "avatars": {
            "small": "http://img7.doubanio.com/img/celebrity/small/4421.jpg",
            "large": "http://img7.doubanio.com/img/celebrity/large/4421.jpg",
            "medium": "http://img7.doubanio.com/img/celebrity/medium/4421.jpg"
          },
          "name": "宋智孝",
          "id": "1023418"
        },
        {
          "alt": "https://movie.douban.com/celebrity/1049467/",
          "avatars": {
            "small": "http://img3.doubanio.com/img/celebrity/small/24606.jpg",
            "large": "http://img3.doubanio.com/img/celebrity/large/24606.jpg",
            "medium": "http://img3.doubanio.com/img/celebrity/medium/24606.jpg"
          },
          "name": "大卫·贝利",
          "id": "1049467"
        }
      ],
      "collect_count": 69,
      "original_title": "超级快递",
      "subtype": "movie",
      "directors": [
        {
          "alt": null,
          "avatars": null,
          "name": "宋啸",
          "id": null
        }
      ],
      "year": "2016",
      "images": {
        "small": "http://img7.doubanio.com/view/movie_poster_cover/ipst/public/p2400235604.jpg",
        "large": "http://img7.doubanio.com/view/movie_poster_cover/lpst/public/p2400235604.jpg",
        "medium": "http://img7.doubanio.com/view/movie_poster_cover/spst/public/p2400235604.jpg"
      },
      "alt": "https://movie.douban.com/subject/26651353/",
      "id": "26651353"
    },
    {
      "rating": {
        "max": 10,
        "average": 0,
        "stars": "00",
        "min": 0
      },
      "genres": [
        "奇幻",
        "恐怖"
      ],
      "title": "食人岛",
      "casts": [
        {
          "alt": "https://movie.douban.com/celebrity/1317811/",
          "avatars": {
            "small": "http://img7.doubanio.com/img/celebrity/small/1360846746.75.jpg",
            "large": "http://img7.doubanio.com/img/celebrity/large/1360846746.75.jpg",
            "medium": "http://img7.doubanio.com/img/celebrity/medium/1360846746.75.jpg"
          },
          "name": "娄淇",
          "id": "1317811"
        },
        {
          "alt": "https://movie.douban.com/celebrity/1340268/",
          "avatars": {
            "small": "http://img3.doubanio.com/img/celebrity/small/1401112685.76.jpg",
            "large": "http://img3.doubanio.com/img/celebrity/large/1401112685.76.jpg",
            "medium": "http://img3.doubanio.com/img/celebrity/medium/1401112685.76.jpg"
          },
          "name": "杨凯迪",
          "id": "1340268"
        },
        {
          "alt": "https://movie.douban.com/celebrity/1353699/",
          "avatars": {
            "small": "http://img7.doubanio.com/img/celebrity/small/1455755779.42.jpg",
            "large": "http://img7.doubanio.com/img/celebrity/large/1455755779.42.jpg",
            "medium": "http://img7.doubanio.com/img/celebrity/medium/1455755779.42.jpg"
          },
          "name": "谢波",
          "id": "1353699"
        }
      ],
      "collect_count": 25,
      "original_title": "食人岛",
      "subtype": "movie",
      "directors": [
        {
          "alt": "https://movie.douban.com/celebrity/1317858/",
          "avatars": {
            "small": "http://img3.doubanio.com/img/celebrity/small/41506.jpg",
            "large": "http://img3.doubanio.com/img/celebrity/large/41506.jpg",
            "medium": "http://img3.doubanio.com/img/celebrity/medium/41506.jpg"
          },
          "name": "李凯",
          "id": "1317858"
        }
      ],
      "year": "2016",
      "images": {
        "small": "http://img3.doubanio.com/view/movie_poster_cover/ipst/public/p2400942579.jpg",
        "large": "http://img3.doubanio.com/view/movie_poster_cover/lpst/public/p2400942579.jpg",
        "medium": "http://img3.doubanio.com/view/movie_poster_cover/spst/public/p2400942579.jpg"
      },
      "alt": "https://movie.douban.com/subject/26840300/",
      "id": "26840300"
    },
    {
      "rating": {
        "max": 10,
        "average": 0,
        "stars": "00",
        "min": 0
      },
      "genres": [
        "喜剧",
        "犯罪",
        "冒险"
      ],
      "title": "冒牌卧底",
      "casts": [
        {
          "alt": "https://movie.douban.com/celebrity/1046960/",
          "avatars": {
            "small": "http://img3.doubanio.com/img/celebrity/small/4376.jpg",
            "large": "http://img3.doubanio.com/img/celebrity/large/4376.jpg",
            "medium": "http://img3.doubanio.com/img/celebrity/medium/4376.jpg"
          },
          "name": "潘粤明",
          "id": "1046960"
        },
        {
          "alt": "https://movie.douban.com/celebrity/1036695/",
          "avatars": {
            "small": "http://img7.doubanio.com/img/celebrity/small/1355297994.85.jpg",
            "large": "http://img7.doubanio.com/img/celebrity/large/1355297994.85.jpg",
            "medium": "http://img7.doubanio.com/img/celebrity/medium/1355297994.85.jpg"
          },
          "name": "高圣远",
          "id": "1036695"
        },
        {
          "alt": "https://movie.douban.com/celebrity/1327084/",
          "avatars": {
            "small": "http://img7.doubanio.com/img/celebrity/small/1363597076.12.jpg",
            "large": "http://img7.doubanio.com/img/celebrity/large/1363597076.12.jpg",
            "medium": "http://img7.doubanio.com/img/celebrity/medium/1363597076.12.jpg"
          },
          "name": "常远",
          "id": "1327084"
        }
      ],
      "collect_count": 8,
      "original_title": "冒牌卧底",
      "subtype": "movie",
      "directors": [
        {
          "alt": "https://movie.douban.com/celebrity/1334343/",
          "avatars": {
            "small": "http://img3.doubanio.com/img/celebrity/small/1441507811.86.jpg",
            "large": "http://img3.doubanio.com/img/celebrity/large/1441507811.86.jpg",
            "medium": "http://img3.doubanio.com/img/celebrity/medium/1441507811.86.jpg"
          },
          "name": "唐旭",
          "id": "1334343"
        }
      ],
      "year": "2016",
      "images": {
        "small": "http://img7.doubanio.com/view/movie_poster_cover/ipst/public/p2389863841.jpg",
        "large": "http://img7.doubanio.com/view/movie_poster_cover/lpst/public/p2389863841.jpg",
        "medium": "http://img7.doubanio.com/view/movie_poster_cover/spst/public/p2389863841.jpg"
      },
      "alt": "https://movie.douban.com/subject/26743534/",
      "id": "26743534"
    },
    {
      "rating": {
        "max": 10,
        "average": 0,
        "stars": "00",
        "min": 0
      },
      "genres": [
        "剧情",
        "爱情",
        "冒险"
      ],
      "title": "沙漠之心",
      "casts": [
        {
          "alt": "https://movie.douban.com/celebrity/1335470/",
          "avatars": {
            "small": "http://img7.doubanio.com/img/celebrity/small/1410187196.93.jpg",
            "large": "http://img7.doubanio.com/img/celebrity/large/1410187196.93.jpg",
            "medium": "http://img7.doubanio.com/img/celebrity/medium/1410187196.93.jpg"
          },
          "name": "隋咏良",
          "id": "1335470"
        },
        {
          "alt": "https://movie.douban.com/celebrity/1343521/",
          "avatars": {
            "small": "http://img3.doubanio.com/img/celebrity/small/42ExNrfRQYcel_avatar_uploaded1412447745.66.jpg",
            "large": "http://img3.doubanio.com/img/celebrity/large/42ExNrfRQYcel_avatar_uploaded1412447745.66.jpg",
            "medium": "http://img3.doubanio.com/img/celebrity/medium/42ExNrfRQYcel_avatar_uploaded1412447745.66.jpg"
          },
          "name": "尤靖茹",
          "id": "1343521"
        },
        {
          "alt": "https://movie.douban.com/celebrity/1364759/",
          "avatars": {
            "small": "http://img3.doubanio.com/f/movie/ca527386eb8c4e325611e22dfcb04cc116d6b423/pics/movie/celebrity-default-small.png",
            "large": "http://img7.doubanio.com/f/movie/63acc16ca6309ef191f0378faf793d1096a3e606/pics/movie/celebrity-default-large.png",
            "medium": "http://img3.doubanio.com/f/movie/8dd0c794499fe925ae2ae89ee30cd225750457b4/pics/movie/celebrity-default-medium.png"
          },
          "name": "薛祺",
          "id": "1364759"
        }
      ],
      "collect_count": 6,
      "original_title": "沙漠之心",
      "subtype": "movie",
      "directors": [
        {
          "alt": "https://movie.douban.com/celebrity/1364757/",
          "avatars": {
            "small": "http://img3.doubanio.com/f/movie/ca527386eb8c4e325611e22dfcb04cc116d6b423/pics/movie/celebrity-default-small.png",
            "large": "http://img7.doubanio.com/f/movie/63acc16ca6309ef191f0378faf793d1096a3e606/pics/movie/celebrity-default-large.png",
            "medium": "http://img3.doubanio.com/f/movie/8dd0c794499fe925ae2ae89ee30cd225750457b4/pics/movie/celebrity-default-medium.png"
          },
          "name": "李柯",
          "id": "1364757"
        }
      ],
      "year": "2016",
      "images": {
        "small": "http://img3.doubanio.com/view/movie_poster_cover/ipst/public/p2396325047.jpg",
        "large": "http://img3.doubanio.com/view/movie_poster_cover/lpst/public/p2396325047.jpg",
        "medium": "http://img3.doubanio.com/view/movie_poster_cover/spst/public/p2396325047.jpg"
      },
      "alt": "https://movie.douban.com/subject/26907466/",
      "id": "26907466"
    },
    {
      "rating": {
        "max": 10,
        "average": 0,
        "stars": "00",
        "min": 0
      },
      "genres": [
        "剧情",
        "动作",
        "科幻"
      ],
      "title": "东宫皇子",
      "casts": [
        {
          "alt": null,
          "avatars": null,
          "name": "姚亦",
          "id": null
        },
        {
          "alt": "https://movie.douban.com/celebrity/1350386/",
          "avatars": {
            "small": "http://img3.doubanio.com/f/movie/ca527386eb8c4e325611e22dfcb04cc116d6b423/pics/movie/celebrity-default-small.png",
            "large": "http://img7.doubanio.com/f/movie/63acc16ca6309ef191f0378faf793d1096a3e606/pics/movie/celebrity-default-large.png",
            "medium": "http://img3.doubanio.com/f/movie/8dd0c794499fe925ae2ae89ee30cd225750457b4/pics/movie/celebrity-default-medium.png"
          },
          "name": "杜乔",
          "id": "1350386"
        },
        {
          "alt": null,
          "avatars": null,
          "name": "陈相丞",
          "id": null
        }
      ],
      "collect_count": 18,
      "original_title": "东宫皇子",
      "subtype": "movie",
      "directors": [
        {
          "alt": null,
          "avatars": null,
          "name": "左伟晨",
          "id": null
        }
      ],
      "year": "2016",
      "images": {
        "small": "http://img3.doubanio.com/view/movie_poster_cover/ipst/public/p2394460517.jpg",
        "large": "http://img3.doubanio.com/view/movie_poster_cover/lpst/public/p2394460517.jpg",
        "medium": "http://img3.doubanio.com/view/movie_poster_cover/spst/public/p2394460517.jpg"
      },
      "alt": "https://movie.douban.com/subject/26883577/",
      "id": "26883577"
    },
    {
      "rating": {
        "max": 10,
        "average": 0,
        "stars": "00",
        "min": 0
      },
      "genres": [
        "喜剧"
      ],
      "title": "试睡员48小时",
      "casts": [
        {
          "alt": "https://movie.douban.com/celebrity/1364624/",
          "avatars": {
            "small": "http://img3.doubanio.com/img/celebrity/small/1478777436.56.jpg",
            "large": "http://img3.doubanio.com/img/celebrity/large/1478777436.56.jpg",
            "medium": "http://img3.doubanio.com/img/celebrity/medium/1478777436.56.jpg"
          },
          "name": "李天烨",
          "id": "1364624"
        },
        {
          "alt": "https://movie.douban.com/celebrity/1351033/",
          "avatars": {
            "small": "http://img7.doubanio.com/img/celebrity/small/1479787817.02.jpg",
            "large": "http://img7.doubanio.com/img/celebrity/large/1479787817.02.jpg",
            "medium": "http://img7.doubanio.com/img/celebrity/medium/1479787817.02.jpg"
          },
          "name": "李婉儿",
          "id": "1351033"
        },
        {
          "alt": "https://movie.douban.com/celebrity/1359006/",
          "avatars": {
            "small": "http://img3.doubanio.com/img/celebrity/small/1465913877.59.jpg",
            "large": "http://img3.doubanio.com/img/celebrity/large/1465913877.59.jpg",
            "medium": "http://img3.doubanio.com/img/celebrity/medium/1465913877.59.jpg"
          },
          "name": "程爽",
          "id": "1359006"
        }
      ],
      "collect_count": 6,
      "original_title": "试睡员48小时",
      "subtype": "movie",
      "directors": [
        {
          "alt": "https://movie.douban.com/celebrity/1332872/",
          "avatars": {
            "small": "http://img7.doubanio.com/img/celebrity/small/1376453026.25.jpg",
            "large": "http://img7.doubanio.com/img/celebrity/large/1376453026.25.jpg",
            "medium": "http://img7.doubanio.com/img/celebrity/medium/1376453026.25.jpg"
          },
          "name": "郭奎永",
          "id": "1332872"
        }
      ],
      "year": "2016",
      "images": {
        "small": "http://img3.doubanio.com/view/movie_poster_cover/ipst/public/p2400074268.jpg",
        "large": "http://img3.doubanio.com/view/movie_poster_cover/lpst/public/p2400074268.jpg",
        "medium": "http://img3.doubanio.com/view/movie_poster_cover/spst/public/p2400074268.jpg"
      },
      "alt": "https://movie.douban.com/subject/26911536/",
      "id": "26911536"
    },
    {
      "rating": {
        "max": 10,
        "average": 8.5,
        "stars": "45",
        "min": 0
      },
      "genres": [
        "剧情",
        "传记",
        "历史"
      ],
      "title": "血战钢锯岭",
      "casts": [
        {
          "alt": "https://movie.douban.com/celebrity/1022620/",
          "avatars": {
            "small": "http://img7.doubanio.com/img/celebrity/small/13151.jpg",
            "large": "http://img7.doubanio.com/img/celebrity/large/13151.jpg",
            "medium": "http://img7.doubanio.com/img/celebrity/medium/13151.jpg"
          },
          "name": "安德鲁·加菲尔德",
          "id": "1022620"
        },
        {
          "alt": "https://movie.douban.com/celebrity/1000147/",
          "avatars": {
            "small": "http://img7.doubanio.com/img/celebrity/small/35783.jpg",
            "large": "http://img7.doubanio.com/img/celebrity/large/35783.jpg",
            "medium": "http://img7.doubanio.com/img/celebrity/medium/35783.jpg"
          },
          "name": "萨姆·沃辛顿",
          "id": "1000147"
        },
        {
          "alt": "https://movie.douban.com/celebrity/1002673/",
          "avatars": {
            "small": "http://img3.doubanio.com/img/celebrity/small/6056.jpg",
            "large": "http://img3.doubanio.com/img/celebrity/large/6056.jpg",
            "medium": "http://img3.doubanio.com/img/celebrity/medium/6056.jpg"
          },
          "name": "文斯·沃恩",
          "id": "1002673"
        }
      ],
      "collect_count": 936,
      "original_title": "Hacksaw Ridge",
      "subtype": "movie",
      "directors": [
        {
          "alt": "https://movie.douban.com/celebrity/1054530/",
          "avatars": {
            "small": "http://img7.doubanio.com/img/celebrity/small/680.jpg",
            "large": "http://img7.doubanio.com/img/celebrity/large/680.jpg",
            "medium": "http://img7.doubanio.com/img/celebrity/medium/680.jpg"
          },
          "name": "梅尔·吉布森",
          "id": "1054530"
        }
      ],
      "year": "2016",
      "images": {
        "small": "http://img3.doubanio.com/view/movie_poster_cover/ipst/public/p2397337958.jpg",
        "large": "http://img3.doubanio.com/view/movie_poster_cover/lpst/public/p2397337958.jpg",
        "medium": "http://img3.doubanio.com/view/movie_poster_cover/spst/public/p2397337958.jpg"
      },
      "alt": "https://movie.douban.com/subject/26325320/",
      "id": "26325320"
    },
    {
      "rating": {
        "max": 10,
        "average": 0,
        "stars": "00",
        "min": 0
      },
      "genres": [
        "剧情",
        "喜剧"
      ],
      "title": "纯洁心灵·逐梦演艺圈",
      "casts": [
        {
          "alt": null,
          "avatars": null,
          "name": "朱哲健",
          "id": null
        },
        {
          "alt": null,
          "avatars": null,
          "name": "李彦漫",
          "id": null
        },
        {
          "alt": null,
          "avatars": null,
          "name": "陈思瀚",
          "id": null
        }
      ],
      "collect_count": 150,
      "original_title": "纯洁心灵·逐梦演艺圈",
      "subtype": "movie",
      "directors": [
        {
          "alt": null,
          "avatars": null,
          "name": "毕志飞",
          "id": null
        }
      ],
      "year": "2016",
      "images": {
        "small": "http://img7.doubanio.com/view/movie_poster_cover/ipst/public/p2371693842.jpg",
        "large": "http://img7.doubanio.com/view/movie_poster_cover/lpst/public/p2371693842.jpg",
        "medium": "http://img7.doubanio.com/view/movie_poster_cover/spst/public/p2371693842.jpg"
      },
      "alt": "https://movie.douban.com/subject/26322774/",
      "id": "26322774"
    },
    {
      "rating": {
        "max": 10,
        "average": 8.2,
        "stars": "45",
        "min": 0
      },
      "genres": [
        "剧情",
        "传记",
        "灾难"
      ],
      "title": "萨利机长",
      "casts": [
        {
          "alt": "https://movie.douban.com/celebrity/1054450/",
          "avatars": {
            "small": "http://img7.doubanio.com/img/celebrity/small/551.jpg",
            "large": "http://img7.doubanio.com/img/celebrity/large/551.jpg",
            "medium": "http://img7.doubanio.com/img/celebrity/medium/551.jpg"
          },
          "name": "汤姆·汉克斯",
          "id": "1054450"
        },
        {
          "alt": "https://movie.douban.com/celebrity/1053577/",
          "avatars": {
            "small": "http://img7.doubanio.com/img/celebrity/small/522.jpg",
            "large": "http://img7.doubanio.com/img/celebrity/large/522.jpg",
            "medium": "http://img7.doubanio.com/img/celebrity/medium/522.jpg"
          },
          "name": "艾伦·艾克哈特",
          "id": "1053577"
        },
        {
          "alt": "https://movie.douban.com/celebrity/1053572/",
          "avatars": {
            "small": "http://img3.doubanio.com/img/celebrity/small/516.jpg",
            "large": "http://img3.doubanio.com/img/celebrity/large/516.jpg",
            "medium": "http://img3.doubanio.com/img/celebrity/medium/516.jpg"
          },
          "name": "劳拉·琳妮",
          "id": "1053572"
        }
      ],
      "collect_count": 5971,
      "original_title": "Sully",
      "subtype": "movie",
      "directors": [
        {
          "alt": "https://movie.douban.com/celebrity/1054436/",
          "avatars": {
            "small": "http://img7.doubanio.com/img/celebrity/small/5064.jpg",
            "large": "http://img7.doubanio.com/img/celebrity/large/5064.jpg",
            "medium": "http://img7.doubanio.com/img/celebrity/medium/5064.jpg"
          },
          "name": "克林特·伊斯特伍德",
          "id": "1054436"
        }
      ],
      "year": "2016",
      "images": {
        "small": "http://img7.doubanio.com/view/movie_poster_cover/ipst/public/p2392455603.jpg",
        "large": "http://img7.doubanio.com/view/movie_poster_cover/lpst/public/p2392455603.jpg",
        "medium": "http://img7.doubanio.com/view/movie_poster_cover/spst/public/p2392455603.jpg"
      },
      "alt": "https://movie.douban.com/subject/26416603/",
      "id": "26416603"
    },
    {
      "rating": {
        "max": 10,
        "average": 7.7,
        "stars": "40",
        "min": 0
      },
      "genres": [
        "剧情"
      ],
      "title": "塔洛",
      "casts": [
        {
          "alt": "https://movie.douban.com/celebrity/1351582/",
          "avatars": {
            "small": "http://img7.doubanio.com/img/celebrity/small/1444236100.24.jpg",
            "large": "http://img7.doubanio.com/img/celebrity/large/1444236100.24.jpg",
            "medium": "http://img7.doubanio.com/img/celebrity/medium/1444236100.24.jpg"
          },
          "name": "西德尼玛",
          "id": "1351582"
        },
        {
          "alt": "https://movie.douban.com/celebrity/1351583/",
          "avatars": {
            "small": "http://img3.doubanio.com/img/celebrity/small/1446572924.57.jpg",
            "large": "http://img3.doubanio.com/img/celebrity/large/1446572924.57.jpg",
            "medium": "http://img3.doubanio.com/img/celebrity/medium/1446572924.57.jpg"
          },
          "name": "杨秀措",
          "id": "1351583"
        }
      ],
      "collect_count": 1458,
      "original_title": "塔洛",
      "subtype": "movie",
      "directors": [
        {
          "alt": "https://movie.douban.com/celebrity/1316181/",
          "avatars": {
            "small": "http://img3.doubanio.com/img/celebrity/small/35478.jpg",
            "large": "http://img3.doubanio.com/img/celebrity/large/35478.jpg",
            "medium": "http://img3.doubanio.com/img/celebrity/medium/35478.jpg"
          },
          "name": "万玛才旦",
          "id": "1316181"
        }
      ],
      "year": "2015",
      "images": {
        "small": "http://img7.doubanio.com/view/movie_poster_cover/ipst/public/p2390837982.jpg",
        "large": "http://img7.doubanio.com/view/movie_poster_cover/lpst/public/p2390837982.jpg",
        "medium": "http://img7.doubanio.com/view/movie_poster_cover/spst/public/p2390837982.jpg"
      },
      "alt": "https://movie.douban.com/subject/26586806/",
      "id": "26586806"
    },
    {
      "rating": {
        "max": 10,
        "average": 6.9,
        "stars": "35",
        "min": 0
      },
      "genres": [
        "剧情",
        "喜剧"
      ],
      "title": "少年巴比伦",
      "casts": [
        {
          "alt": "https://movie.douban.com/celebrity/1330472/",
          "avatars": {
            "small": "http://img7.doubanio.com/img/celebrity/small/1385100761.5.jpg",
            "large": "http://img7.doubanio.com/img/celebrity/large/1385100761.5.jpg",
            "medium": "http://img7.doubanio.com/img/celebrity/medium/1385100761.5.jpg"
          },
          "name": "董子健",
          "id": "1330472"
        },
        {
          "alt": "https://movie.douban.com/celebrity/1317539/",
          "avatars": {
            "small": "http://img7.doubanio.com/img/celebrity/small/40311.jpg",
            "large": "http://img7.doubanio.com/img/celebrity/large/40311.jpg",
            "medium": "http://img7.doubanio.com/img/celebrity/medium/40311.jpg"
          },
          "name": "李梦",
          "id": "1317539"
        },
        {
          "alt": "https://movie.douban.com/celebrity/1326042/",
          "avatars": {
            "small": "http://img7.doubanio.com/img/celebrity/small/1357696338.94.jpg",
            "large": "http://img7.doubanio.com/img/celebrity/large/1357696338.94.jpg",
            "medium": "http://img7.doubanio.com/img/celebrity/medium/1357696338.94.jpg"
          },
          "name": "尚铁龙",
          "id": "1326042"
        }
      ],
      "collect_count": 706,
      "original_title": "少年巴比伦",
      "subtype": "movie",
      "directors": [
        {
          "alt": "https://movie.douban.com/celebrity/1349688/",
          "avatars": {
            "small": "http://img3.doubanio.com/img/celebrity/small/1477215027.26.jpg",
            "large": "http://img3.doubanio.com/img/celebrity/large/1477215027.26.jpg",
            "medium": "http://img3.doubanio.com/img/celebrity/medium/1477215027.26.jpg"
          },
          "name": "相国强",
          "id": "1349688"
        }
      ],
      "year": "2015",
      "images": {
        "small": "http://img7.doubanio.com/view/movie_poster_cover/ipst/public/p2390347404.jpg",
        "large": "http://img7.doubanio.com/view/movie_poster_cover/lpst/public/p2390347404.jpg",
        "medium": "http://img7.doubanio.com/view/movie_poster_cover/spst/public/p2390347404.jpg"
      },
      "alt": "https://movie.douban.com/subject/25876760/",
      "id": "25876760"
    },
    {
      "rating": {
        "max": 10,
        "average": 0,
        "stars": "00",
        "min": 0
      },
      "genres": [
        "剧情",
        "犯罪",
        "悬疑"
      ],
      "title": "嫌疑人X的献身",
      "casts": [
        {
          "alt": "https://movie.douban.com/celebrity/1314544/",
          "avatars": {
            "small": "http://img7.doubanio.com/img/celebrity/small/1444998211.72.jpg",
            "large": "http://img7.doubanio.com/img/celebrity/large/1444998211.72.jpg",
            "medium": "http://img7.doubanio.com/img/celebrity/medium/1444998211.72.jpg"
          },
          "name": "王凯",
          "id": "1314544"
        },
        {
          "alt": "https://movie.douban.com/celebrity/1312846/",
          "avatars": {
            "small": "http://img3.doubanio.com/img/celebrity/small/39129.jpg",
            "large": "http://img3.doubanio.com/img/celebrity/large/39129.jpg",
            "medium": "http://img3.doubanio.com/img/celebrity/medium/39129.jpg"
          },
          "name": "柳岩",
          "id": "1312846"
        },
        {
          "alt": "https://movie.douban.com/celebrity/1323723/",
          "avatars": {
            "small": "http://img7.doubanio.com/img/celebrity/small/1416748988.73.jpg",
            "large": "http://img7.doubanio.com/img/celebrity/large/1416748988.73.jpg",
            "medium": "http://img7.doubanio.com/img/celebrity/medium/1416748988.73.jpg"
          },
          "name": "张鲁一",
          "id": "1323723"
        }
      ],
      "collect_count": 252,
      "original_title": "嫌疑人X的献身",
      "subtype": "movie",
      "directors": [
        {
          "alt": "https://movie.douban.com/celebrity/1050540/",
          "avatars": {
            "small": "http://img3.doubanio.com/img/celebrity/small/1370314365.18.jpg",
            "large": "http://img3.doubanio.com/img/celebrity/large/1370314365.18.jpg",
            "medium": "http://img3.doubanio.com/img/celebrity/medium/1370314365.18.jpg"
          },
          "name": "苏有朋",
          "id": "1050540"
        }
      ],
      "year": "2016",
      "images": {
        "small": "http://img3.doubanio.com/view/movie_poster_cover/ipst/public/p2371820307.jpg",
        "large": "http://img3.doubanio.com/view/movie_poster_cover/lpst/public/p2371820307.jpg",
        "medium": "http://img3.doubanio.com/view/movie_poster_cover/spst/public/p2371820307.jpg"
      },
      "alt": "https://movie.douban.com/subject/26606743/",
      "id": "26606743"
    },
    {
      "rating": {
        "max": 10,
        "average": 0,
        "stars": "00",
        "min": 0
      },
      "genres": [
        "剧情",
        "爱情",
        "犯罪"
      ],
      "title": "那年夏天你去了哪里",
      "casts": [
        {
          "alt": "https://movie.douban.com/celebrity/1042341/",
          "avatars": {
            "small": "http://img7.doubanio.com/img/celebrity/small/23241.jpg",
            "large": "http://img7.doubanio.com/img/celebrity/large/23241.jpg",
            "medium": "http://img7.doubanio.com/img/celebrity/medium/23241.jpg"
          },
          "name": "宋佳",
          "id": "1042341"
        },
        {
          "alt": "https://movie.douban.com/celebrity/1050329/",
          "avatars": {
            "small": "http://img7.doubanio.com/img/celebrity/small/1408428669.04.jpg",
            "large": "http://img7.doubanio.com/img/celebrity/large/1408428669.04.jpg",
            "medium": "http://img7.doubanio.com/img/celebrity/medium/1408428669.04.jpg"
          },
          "name": "林家栋",
          "id": "1050329"
        },
        {
          "alt": "https://movie.douban.com/celebrity/1318260/",
          "avatars": {
            "small": "http://img3.doubanio.com/img/celebrity/small/1385270440.49.jpg",
            "large": "http://img3.doubanio.com/img/celebrity/large/1385270440.49.jpg",
            "medium": "http://img3.doubanio.com/img/celebrity/medium/1385270440.49.jpg"
          },
          "name": "颜卓灵",
          "id": "1318260"
        }
      ],
      "collect_count": 97,
      "original_title": "那年夏天你去了哪里",
      "subtype": "movie",
      "directors": [
        {
          "alt": "https://movie.douban.com/celebrity/1332644/",
          "avatars": {
            "small": "http://img7.doubanio.com/img/celebrity/small/1479787650.12.jpg",
            "large": "http://img7.doubanio.com/img/celebrity/large/1479787650.12.jpg",
            "medium": "http://img7.doubanio.com/img/celebrity/medium/1479787650.12.jpg"
          },
          "name": "周隼",
          "id": "1332644"
        }
      ],
      "year": "2016",
      "images": {
        "small": "http://img7.doubanio.com/view/movie_poster_cover/ipst/public/p2399122623.jpg",
        "large": "http://img7.doubanio.com/view/movie_poster_cover/lpst/public/p2399122623.jpg",
        "medium": "http://img7.doubanio.com/view/movie_poster_cover/spst/public/p2399122623.jpg"
      },
      "alt": "https://movie.douban.com/subject/26876595/",
      "id": "26876595"
    }
  ],
  "title": "即将上映的电影"
}